py_load
