Metadata-Version: 2.1
Name: py-load-lib
Version: 0.5
Summary: A super simple, compact, and easy to use loading bar module for python with no dependencies.
Home-page: https://github.com/talwat/py-load
Author: Talwat
Author-email: talwat321@gmail.com
License: MIT
Project-URL: Wiki, https://github.com/talwat/py-load/wiki
Keywords: loading,bar,loadingbar,loading bar,progressbar,progressmeter,progress,bar,meter,rate,eta,console,terminal,time
Platform: any
Classifier: Programming Language :: Python :: 3
Classifier: License :: OSI Approved :: MIT License
Classifier: Operating System :: OS Independent
Requires-Python: >=3.6
